odoo/addons/pos_empty_home/README.rst
odoo/addons/pos_empty_home/__init__.py
odoo/addons/pos_empty_home/__manifest__.py
odoo/addons/pos_empty_home/i18n/ca.po
odoo/addons/pos_empty_home/i18n/es.po
odoo/addons/pos_empty_home/i18n/fr.po
odoo/addons/pos_empty_home/i18n/it.po
odoo/addons/pos_empty_home/i18n/pos_empty_home.pot
odoo/addons/pos_empty_home/readme/CONTRIBUTORS.rst
odoo/addons/pos_empty_home/readme/DESCRIPTION.rst
odoo/addons/pos_empty_home/static/description/icon.png
odoo/addons/pos_empty_home/static/description/index.html
odoo/addons/pos_empty_home/static/description/pos_empty_home.png
odoo/addons/pos_empty_home/static/src/css/pos_empty_home.css
odoo/addons/pos_empty_home/static/src/js/db.js
odoo/addons/pos_empty_home/static/src/js/screens.js
odoo/addons/pos_empty_home/static/src/xml/pos_empty_home.xml
odoo/addons/pos_empty_home/views/assets.xml
odoo12_addon_pos_empty_home-12.0.1.0.1.dist-info/METADATA
odoo12_addon_pos_empty_home-12.0.1.0.1.dist-info/WHEEL
odoo12_addon_pos_empty_home-12.0.1.0.1.dist-info/top_level.txt
odoo12_addon_pos_empty_home-12.0.1.0.1.dist-info/RECORD
